Booth_algo/ba.v
`timescale 1ns/1ps
module booths_algo #(
    parameter N = 4           
)(
    input clk,                // Clock 
    input rst,                // Active-high reset
    input [N-1:0] mr_in,      // Multiplier
    input [N-1:0] md,         // Multiplicand
    output reg [2*N-1:0] out  // Final Product (2*N bits)
);

    
    reg [N-1:0] mr;           // Multiplier register
    reg [N-1:0] accu;         // Accumulator
    reg [N-1:0] arth;         // Arithmetic temporary reg 
    reg q1;                   // Booth’s extra bit
    reg [N-1:0] inv_md;       // Two’s complement of multiplicand
    reg [$clog2(N):0] count;  // Counter (steps= no. of bits input have)


    always @(posedge clk or posedge rst) begin
        if (rst) begin
            mr     = mr_in;           // Load multiplier
            accu   = {N{1'b0}};       // Clear accumulator
            q1     = 1'b0;            // Reset q1
            inv_md = ~md + 1;         // Compute 2's complement of md
            count  = N;               // Set iteration count
            out    = {2*N{1'b0}};     // Clear output
        end 
        else if (count != 0) begin
            // Step 1: Booth’s Decision Logic
            if (mr[0] & ~q1)
                arth = accu + inv_md;   // 0->1; Subtract multiplicand

            else if (~mr[0] & q1)
                arth = accu + md;       // 1->0 ; Add multiplicand
                
            else
                arth = accu;            // no transition → No operation

            // Step 2: Arithmetic Right Shift
            q1  = mr[0];                           // Update q1
            mr  = {arth[0], mr[N-1:1]};            // Shift MR with sign bit
            accu = {arth[N-1], arth[N-1:1]};       // Shift Accumulator with sign bit

            count = count - 1;

            // Step 3: Store Final Product After N Iterations
            if (count == 0) begin
                out = {accu, mr};       // Concatenate ACCU and MR
            end
        end
    end

endmodule

Booth_algo/ba_tb.v
`timescale 1ns/1ps

module tb_booths_algo;

    parameter N = 4;
    parameter Tclk = 10; 
  
    reg clk;
    reg rst;
    reg [N-1:0] mr_in;
    reg [N-1:0] md;
    wire [2*N-1:0] out;

    // Instantiate the Booth's multiplier
    booths_algo #(N) uut (
        .clk(clk),
        .rst(rst),
        .mr_in(mr_in),
        .md(md),
        .out(out)
    );

    // Clock generation: 10ns period
    initial clk = 0;
    always #(Tclk/2) clk = ~clk;

    // Test sequence
    initial begin
        // Dump waveform
        $dumpfile("booths_shift.vcd");
        $dumpvars(0, tb_booths_algo);

        // Test Case 1
        rst = 1;
        mr_in = 4'b0111; //7
        md    = 4'b0101; //5
        #10;
        rst = 0;
        
        #(Tclk * (N + 1));              // Wait for N iterations

         $display("Final Output => Time=%0t | Multiplier=%0d | Multiplicant=%0d | Output=%0d",
         $time, $signed(mr_in), $signed(md), $signed(out));

        
        // Test Case 2
        rst = 1; 
        mr_in = 4'b0011;  //3
        md    = 4'b1011;  //-5
        #10;
        rst = 0;
        
      #(Tclk * (N + 1));               // Wait for N iterations
       
      $display("Final Output => Time=%0t | Multiplier=%0d | Multiplicant=%0d | Output=%0d",
         $time, $signed(mr_in), $signed(md), $signed(out));


        $finish;
    end

    // Optional: print output at each positive edge
    always @(posedge clk) begin
        $display("Time=%0t | ACC=%b | MR=%b | OUT=%b", $time, uut.accu, uut.mr, out);
    end

endmodule

Booth_algo/booths_shift.vcd
$date
	Mon Oct  6 21:00:31 2025
$end
$version
	Icarus Verilog
$end
$timescale
	1ps
$end
$scope module tb_booths_algo $end
$var wire 8 ! out [7:0] $end
$var parameter 32 " N $end
$var parameter 32 # Tclk $end
$var reg 1 $ clk $end
$var reg 4 % md [3:0] $end
$var reg 4 & mr_in [3:0] $end
$var reg 1 ' rst $end
$scope module uut $end
$var wire 1 $ clk $end
$var wire 4 ( md [3:0] $end
$var wire 4 ) mr_in [3:0] $end
$var wire 1 ' rst $end
$var parameter 32 * N $end
$var reg 4 + accu [3:0] $end
$var reg 4 , arth [3:0] $end
$var reg 3 - count [2:0] $end
$var reg 4 . inv_md [3:0] $end
$var reg 4 / mr [3:0] $end
$var reg 8 0 out [7:0] $end
$var reg 1 1 q1 $end
$upscope $end
$upscope $end
$enddefinitions $end
$comment Show the parameter values. $end
$dumpall
b100 *
b1010 #
b100 "
$end
#0
$dumpvars
01
b0 0
b111 /
b1011 .
b100 -
bx ,
b0 +
b111 )
b101 (
1'
b111 &
b101 %
0$
b0 !
$end
#5000
1$
#10000
0$
0'
#15000
b11 -
b1101 +
b1011 /
11
b1011 ,
1$
#20000
0$
#25000
b10 -
b1110 +
b1101 /
b1101 ,
1$
#30000
0$
#35000
b1 -
b1111 +
b110 /
b1110 ,
1$
#40000
0$
#45000
b100011 !
b100011 0
b0 -
b10 +
b11 /
01
b100 ,
1$
#50000
0$
#55000
1$
#60000
b0 !
b0 0
b100 -
b101 .
b0 +
0$
b1011 %
b1011 (
b11 &
b11 )
1'
#65000
1$
#70000
0$
0'
#75000
b11 -
b10 +
b1001 /
11
b101 ,
1$
#80000
0$
#85000
b10 -
b1 +
b100 /
b10 ,
1$
#90000
0$
#95000
b1 -
b1110 +
b10 /
01
b1100 ,
1$
#100000
0$
#105000
b11110001 !
b11110001 0
b0 -
b1111 +
b1 /
b1110 ,
1$
